{
  "data": {
    "article": {},
    "attachments": {},
    "author_id": "1565981667746914304",
    "conversation_id": "2005921019283018122",
    "created_at": "2025-12-30T08:36:53.000Z",
    "edit_controls": {
      "editable_until": "2025-12-30T09:36:53.000Z",
      "edits_remaining": 5,
      "is_edit_eligible": true
    },
    "edit_history_tweet_ids": [
      "2005921019283018122"
    ],
    "entities": {
      "urls": [
        {
          "display_url": "x.com/xiaohuihuih/st…",
          "end": 44,
          "expanded_url": "https://twitter.com/xiaohuihuih/status/2005895454131650791",
          "start": 21,
          "url": "https://t.co/uiwlqz2tno"
        }
      ]
    },
    "geo": {},
    "id": "2005921019283018122",
    "lang": "zh",
    "note_tweet": {
      "entities": {}
    },
    "possibly_sensitive": false,
    "public_metrics": {
      "bookmark_count": 0,
      "impression_count": 0,
      "like_count": 0,
      "quote_count": 0,
      "reply_count": 0,
      "retweet_count": 0
    },
    "referenced_tweets": [
      {
        "id": "2005895454131650791",
        "type": "quoted"
      }
    ],
    "reply_settings": "everyone",
    "text": "我不害怕鬼，鬼不会伤我分毫；\n我怕人…… https://t.co/uiwlqz2tno"
  },
  "includes": {
    "tweets": [
      {
        "article": {},
        "attachments": {},
        "author_id": "1565981667746914304",
        "conversation_id": "2005921019283018122",
        "created_at": "2025-12-30T08:36:53.000Z",
        "edit_controls": {
          "editable_until": "2025-12-30T09:36:53.000Z",
          "edits_remaining": 5,
          "is_edit_eligible": true
        },
        "edit_history_tweet_ids": [
          "2005921019283018122"
        ],
        "entities": {
          "urls": [
            {
              "display_url": "x.com/xiaohuihuih/st…",
              "end": 44,
              "expanded_url": "https://twitter.com/xiaohuihuih/status/2005895454131650791",
              "start": 21,
              "url": "https://t.co/uiwlqz2tno"
            }
          ]
        },
        "geo": {},
        "id": "2005921019283018122",
        "lang": "zh",
        "note_tweet": {
          "entities": {}
        },
        "possibly_sensitive": false,
        "public_metrics": {
          "bookmark_count": 0,
          "impression_count": 0,
          "like_count": 0,
          "quote_count": 0,
          "reply_count": 0,
          "retweet_count": 0
        },
        "referenced_tweets": [
          {
            "id": "2005895454131650791",
            "type": "quoted"
          }
        ],
        "reply_settings": "everyone",
        "text": "我不害怕鬼，鬼不会伤我分毫；\n我怕人…… https://t.co/uiwlqz2tno"
      },
      {
        "article": {},
        "attachments": {},
        "author_id": "1587653801305153538",
        "conversation_id": "2005895454131650791",
        "created_at": "2025-12-30T06:55:18.000Z",
        "edit_controls": {
          "editable_until": "2025-12-30T07:55:18.000Z",
          "edits_remaining": 5,
          "is_edit_eligible": true
        },
        "edit_history_tweet_ids": [
          "2005895454131650791"
        ],
        "entities": {},
        "geo": {},
        "id": "2005895454131650791",
        "lang": "zh",
        "note_tweet": {
          "entities": {}
        },
        "possibly_sensitive": false,
        "public_metrics": {
          "bookmark_count": 0,
          "impression_count": 103,
          "like_count": 7,
          "quote_count": 1,
          "reply_count": 0,
          "retweet_count": 0
        },
        "reply_settings": "everyone",
        "text": "我不害怕鬼，鬼不会伤我分毫；\n我怕人……"
      }
    ],
    "users": [
      {
        "created_at": "2022-09-03T08:35:06.000Z",
        "description": "MTF🏳️‍⚧️trans girl🍥 |09|HRT since 2025.03.19|A student |want to be friends with everyone  |en/cn/日本語初心者|ここは日常しかないよ| 詳しい内容はトップをご覧ください。",
        "id": "1565981667746914304",
        "location": "People's Republic of China",
        "name": "神楽坂　雪風🏳️‍⚧️🍥",
        "pinned_tweet_id": "2004093206515142661",
        "profile_image_url": "https://pbs.twimg.com/profile_images/1998075130380189700/F39f69AX_normal.jpg",
        "protected": false,
        "public_metrics": {
          "followers_count": 2063,
          "following_count": 2157,
          "like_count": 78905,
          "listed_count": 2,
          "media_count": 582,
          "tweet_count": 8998
        },
        "username": "Kagura_Yukikaze",
        "verified": true
      },
      {
        "created_at": "2022-11-02T03:52:34.000Z",
        "description": "好东西曾在咱主页的“亮点”里🥹\n/日常+抽象+涩涩推🫣/\nmtx(f)🏳️‍⚧️但可以把我当男娘喵🏳️‍🌈/含糖🍥2023.12.7/不堪风流往事🩷💜/？？岁/上岸啦，不再约炮和援交/❤️\n@Mirro_zinuo\n/多伦多🇨🇦/\n\n免责避雷声明⚠️地狱笑话+抽象批/温柔+发癫集合体/地雷嗑学家💊",
        "entities": {
          "description": {
            "mentions": [
              {
                "end": 107,
                "start": 95,
                "username": "Mirro_zinuo"
              }
            ]
          },
          "url": {
            "urls": [
              {
                "display_url": "youtube.com/@XiaoHuiHuiH",
                "end": 23,
                "expanded_url": "https://www.youtube.com/@XiaoHuiHuiH",
                "start": 0,
                "url": "https://t.co/LQg5S7YXOr"
              }
            ]
          }
        },
        "id": "1587653801305153538",
        "location": "Toronto, Ontario🇨🇦",
        "name": "小咴咴喵(⁠≧⁠▽⁠≦⁠)/🍥喵喵艺术家~",
        "pinned_tweet_id": "1973169992570118470",
        "profile_image_url": "https://pbs.twimg.com/profile_images/1904236723636224000/W8Cl9P5f_normal.jpg",
        "protected": false,
        "public_metrics": {
          "followers_count": 11834,
          "following_count": 1408,
          "like_count": 156393,
          "listed_count": 25,
          "media_count": 4944,
          "tweet_count": 66573
        },
        "url": "https://t.co/LQg5S7YXOr",
        "username": "XiaoHuiHuiH",
        "verified": true
      }
    ]
  }
}