{
  "data": {
    "article": {},
    "attachments": {
      "media_keys": [
        "3_2018625406522490880"
      ],
      "media_source_tweet_id": [
        "2018626533444014375"
      ]
    },
    "author_id": "1565981667746914304",
    "conversation_id": "2018935329907159344",
    "created_at": "2026-02-04T06:31:07.000Z",
    "edit_controls": {
      "editable_until": "2026-02-04T07:31:07.000Z",
      "edits_remaining": 5,
      "is_edit_eligible": false
    },
    "edit_history_tweet_ids": [
      "2018935329907159344"
    ],
    "entities": {
      "mentions": [
        {
          "end": 12,
          "id": "1102791182092972034",
          "start": 3,
          "username": "Colon_BR"
        }
      ],
      "urls": [
        {
          "display_url": "pic.x.com/dAbBgo8b68",
          "end": 91,
          "expanded_url": "https://x.com/Colon_BR/status/2018626533444014375/photo/1",
          "media_key": "3_2018625406522490880",
          "start": 68,
          "url": "https://t.co/dAbBgo8b68"
        }
      ]
    },
    "geo": {},
    "id": "2018935329907159344",
    "lang": "ja",
    "note_tweet": {
      "entities": {}
    },
    "possibly_sensitive": false,
    "public_metrics": {
      "bookmark_count": 0,
      "impression_count": 0,
      "like_count": 0,
      "quote_count": 0,
      "reply_count": 0,
      "retweet_count": 192
    },
    "referenced_tweets": [
      {
        "id": "2018626533444014375",
        "type": "retweeted"
      }
    ],
    "reply_settings": "everyone",
    "text": "RT @Colon_BR: Skebリクエストありがとうございます！！\nゆーねさん家のにあちゃん描かせていただきました🐾\nかわいいね… https://t.co/dAbBgo8b68"
  },
  "includes": {
    "media": [
      {
        "height": 2830,
        "media_key": "3_2018625406522490880",
        "public_metrics": {},
        "type": "photo",
        "url": "https://pbs.twimg.com/media/HAOZHLJaAAA6ehd.jpg",
        "width": 1886
      }
    ],
    "tweets": [
      {
        "article": {},
        "attachments": {
          "media_keys": [
            "3_2018625406522490880"
          ],
          "media_source_tweet_id": [
            "2018626533444014375"
          ]
        },
        "author_id": "1565981667746914304",
        "conversation_id": "2018935329907159344",
        "created_at": "2026-02-04T06:31:07.000Z",
        "edit_controls": {
          "editable_until": "2026-02-04T07:31:07.000Z",
          "edits_remaining": 5,
          "is_edit_eligible": false
        },
        "edit_history_tweet_ids": [
          "2018935329907159344"
        ],
        "entities": {
          "mentions": [
            {
              "end": 12,
              "id": "1102791182092972034",
              "start": 3,
              "username": "Colon_BR"
            }
          ],
          "urls": [
            {
              "display_url": "pic.x.com/dAbBgo8b68",
              "end": 91,
              "expanded_url": "https://x.com/Colon_BR/status/2018626533444014375/photo/1",
              "media_key": "3_2018625406522490880",
              "start": 68,
              "url": "https://t.co/dAbBgo8b68"
            }
          ]
        },
        "geo": {},
        "id": "2018935329907159344",
        "lang": "ja",
        "note_tweet": {
          "entities": {}
        },
        "possibly_sensitive": false,
        "public_metrics": {
          "bookmark_count": 0,
          "impression_count": 0,
          "like_count": 0,
          "quote_count": 0,
          "reply_count": 0,
          "retweet_count": 192
        },
        "referenced_tweets": [
          {
            "id": "2018626533444014375",
            "type": "retweeted"
          }
        ],
        "reply_settings": "everyone",
        "text": "RT @Colon_BR: Skebリクエストありがとうございます！！\nゆーねさん家のにあちゃん描かせていただきました🐾\nかわいいね… https://t.co/dAbBgo8b68"
      },
      {
        "article": {},
        "attachments": {
          "media_keys": [
            "3_2018625406522490880"
          ]
        },
        "author_id": "1102791182092972034",
        "conversation_id": "2018626533444014375",
        "created_at": "2026-02-03T10:04:04.000Z",
        "edit_controls": {
          "editable_until": "2026-02-03T11:04:04.000Z",
          "edits_remaining": 5,
          "is_edit_eligible": true
        },
        "edit_history_tweet_ids": [
          "2018626533444014375"
        ],
        "entities": {
          "urls": [
            {
              "display_url": "pic.x.com/dAbBgo8b68",
              "end": 77,
              "expanded_url": "https://x.com/Colon_BR/status/2018626533444014375/photo/1",
              "media_key": "3_2018625406522490880",
              "start": 54,
              "url": "https://t.co/dAbBgo8b68"
            }
          ]
        },
        "geo": {},
        "id": "2018626533444014375",
        "lang": "ja",
        "note_tweet": {
          "entities": {}
        },
        "possibly_sensitive": false,
        "public_metrics": {
          "bookmark_count": 139,
          "impression_count": 16109,
          "like_count": 1723,
          "quote_count": 0,
          "reply_count": 5,
          "retweet_count": 192
        },
        "reply_settings": "everyone",
        "text": "Skebリクエストありがとうございます！！\nゆーねさん家のにあちゃん描かせていただきました🐾\nかわいいね… https://t.co/dAbBgo8b68"
      }
    ],
    "users": [
      {
        "created_at": "2022-09-03T08:35:06.000Z",
        "description": "MTF🏳️‍⚧️trans girl🍥 |09|HRT since 2025.03.19|A student |want to be friends with everyone |en/cn/日本語初心者|ここは日常しかないよ| 詳しい内容はトップをご覧ください。",
        "entities": {
          "url": {
            "urls": [
              {
                "display_url": "t.me/Kagura_Yukikaze",
                "end": 23,
                "expanded_url": "https://t.me/Kagura_Yukikaze",
                "start": 0,
                "url": "https://t.co/MVCsywa4YV"
              }
            ]
          }
        },
        "id": "1565981667746914304",
        "location": "People's Republic of China",
        "name": "神楽坂　雪風🏳️‍⚧️🍥",
        "pinned_tweet_id": "2015392548286824749",
        "profile_image_url": "https://pbs.twimg.com/profile_images/2018729886836576256/SFIOxMhw_normal.jpg",
        "protected": false,
        "public_metrics": {
          "followers_count": 2307,
          "following_count": 2362,
          "like_count": 84754,
          "listed_count": 2,
          "media_count": 624,
          "tweet_count": 9951
        },
        "url": "https://t.co/MVCsywa4YV",
        "username": "Kagura_Yukikaze",
        "verified": false
      },
      {
        "created_at": "2019-03-05T04:41:21.000Z",
        "description": "けもみみをよく描きます。 コーヒーともふもふを糧としています。□Skeb→https://t.co/fD7d6slye7 ※Unauthorized reｰuploading & AI training is prohibited",
        "entities": {
          "description": {
            "urls": [
              {
                "display_url": "skeb.jp/@Colon_BR",
                "end": 60,
                "expanded_url": "https://skeb.jp/@Colon_BR",
                "start": 37,
                "url": "https://t.co/fD7d6slye7"
              }
            ]
          },
          "url": {
            "urls": [
              {
                "display_url": "pixiv.net/users/55411005",
                "end": 23,
                "expanded_url": "https://www.pixiv.net/users/55411005",
                "start": 0,
                "url": "https://t.co/L20GflOzRK"
              }
            ]
          }
        },
        "id": "1102791182092972034",
        "location": "地球ねこ",
        "name": "ころんびぁ☕️ 冬コミ2日目西ひ44a",
        "pinned_tweet_id": "2003424125256368330",
        "profile_image_url": "https://pbs.twimg.com/profile_images/1774786243886489600/FHdcbK8I_normal.jpg",
        "protected": false,
        "public_metrics": {
          "followers_count": 29342,
          "following_count": 976,
          "like_count": 51518,
          "listed_count": 325,
          "media_count": 820,
          "tweet_count": 20148
        },
        "url": "https://t.co/L20GflOzRK",
        "username": "Colon_BR",
        "verified": false
      }
    ]
  }
}