{
  "data": {
    "article": {},
    "attachments": {
      "media_keys": [
        "3_2062980330789978112"
      ],
      "media_source_tweet_id": [
        "2062980335382761538"
      ]
    },
    "author_id": "1565981667746914304",
    "conversation_id": "2063185108614738049",
    "created_at": "2026-06-06T09:03:56.000Z",
    "edit_controls": {
      "editable_until": "2026-06-06T10:03:56.000Z",
      "edits_remaining": 5,
      "is_edit_eligible": false
    },
    "edit_history_tweet_ids": [
      "2063185108614738049"
    ],
    "entities": {
      "mentions": [
        {
          "end": 16,
          "id": "1668422443831291905",
          "start": 3,
          "username": "Dawns_Gaming"
        }
      ],
      "urls": [
        {
          "display_url": "pic.x.com/Pc8XzkIpSu",
          "end": 80,
          "expanded_url": "https://x.com/Dawns_Gaming/status/2062980335382761538/photo/1",
          "media_key": "3_2062980330789978112",
          "start": 57,
          "url": "https://t.co/Pc8XzkIpSu"
        }
      ]
    },
    "geo": {},
    "id": "2063185108614738049",
    "lang": "en",
    "note_tweet": {
      "entities": {}
    },
    "possibly_sensitive": false,
    "public_metrics": {
      "bookmark_count": 0,
      "impression_count": 0,
      "like_count": 0,
      "quote_count": 0,
      "reply_count": 0,
      "retweet_count": 134
    },
    "referenced_tweets": [
      {
        "id": "2062980335382761538",
        "type": "retweeted"
      }
    ],
    "reply_settings": "everyone",
    "text": "RT @Dawns_Gaming: Amazing work that my oshis can do this https://t.co/Pc8XzkIpSu"
  },
  "includes": {
    "media": [
      {
        "height": 1080,
        "media_key": "3_2062980330789978112",
        "public_metrics": {},
        "type": "photo",
        "url": "https://pbs.twimg.com/media/HKEtrkNawAAYUB1.jpg",
        "width": 1920
      }
    ],
    "tweets": [
      {
        "article": {},
        "attachments": {
          "media_keys": [
            "3_2062980330789978112"
          ],
          "media_source_tweet_id": [
            "2062980335382761538"
          ]
        },
        "author_id": "1565981667746914304",
        "conversation_id": "2063185108614738049",
        "created_at": "2026-06-06T09:03:56.000Z",
        "edit_controls": {
          "editable_until": "2026-06-06T10:03:56.000Z",
          "edits_remaining": 5,
          "is_edit_eligible": false
        },
        "edit_history_tweet_ids": [
          "2063185108614738049"
        ],
        "entities": {
          "mentions": [
            {
              "end": 16,
              "id": "1668422443831291905",
              "start": 3,
              "username": "Dawns_Gaming"
            }
          ],
          "urls": [
            {
              "display_url": "pic.x.com/Pc8XzkIpSu",
              "end": 80,
              "expanded_url": "https://x.com/Dawns_Gaming/status/2062980335382761538/photo/1",
              "media_key": "3_2062980330789978112",
              "start": 57,
              "url": "https://t.co/Pc8XzkIpSu"
            }
          ]
        },
        "geo": {},
        "id": "2063185108614738049",
        "lang": "en",
        "note_tweet": {
          "entities": {}
        },
        "possibly_sensitive": false,
        "public_metrics": {
          "bookmark_count": 0,
          "impression_count": 0,
          "like_count": 0,
          "quote_count": 0,
          "reply_count": 0,
          "retweet_count": 134
        },
        "referenced_tweets": [
          {
            "id": "2062980335382761538",
            "type": "retweeted"
          }
        ],
        "reply_settings": "everyone",
        "text": "RT @Dawns_Gaming: Amazing work that my oshis can do this https://t.co/Pc8XzkIpSu"
      },
      {
        "article": {},
        "attachments": {
          "media_keys": [
            "3_2062980330789978112"
          ]
        },
        "author_id": "1668422443831291905",
        "conversation_id": "2062980335382761538",
        "created_at": "2026-06-05T19:30:14.000Z",
        "edit_controls": {
          "editable_until": "2026-06-05T20:30:14.000Z",
          "edits_remaining": 5,
          "is_edit_eligible": true
        },
        "edit_history_tweet_ids": [
          "2062980335382761538"
        ],
        "entities": {
          "urls": [
            {
              "display_url": "pic.x.com/Pc8XzkIpSu",
              "end": 62,
              "expanded_url": "https://x.com/Dawns_Gaming/status/2062980335382761538/photo/1",
              "media_key": "3_2062980330789978112",
              "start": 39,
              "url": "https://t.co/Pc8XzkIpSu"
            }
          ]
        },
        "geo": {},
        "id": "2062980335382761538",
        "lang": "en",
        "note_tweet": {
          "entities": {}
        },
        "possibly_sensitive": false,
        "public_metrics": {
          "bookmark_count": 47,
          "impression_count": 7412,
          "like_count": 1124,
          "quote_count": 0,
          "reply_count": 4,
          "retweet_count": 134
        },
        "reply_settings": "everyone",
        "text": "Amazing work that my oshis can do this https://t.co/Pc8XzkIpSu"
      }
    ],
    "users": [
      {
        "created_at": "2022-09-03T08:35:06.000Z",
        "derived": {
          "locations": [
            {
              "country_code": "CN",
              "full_name": "China",
              "geo": {
                "coordinates": [
                  105.0,
                  35.0
                ],
                "type": "Point"
              }
            }
          ]
        },
        "description": "总觉得还有时间，总觉得还有明年，工作太忙日子还长连问候都会忘，别等到世事无常，别等到变了模样\n我想像她一样去拥抱死亡——《124米的距离》",
        "entities": {
          "url": {
            "urls": [
              {
                "display_url": "t.me/Kagura_Yukikaze",
                "end": 23,
                "expanded_url": "https://t.me/Kagura_Yukikaze",
                "start": 0,
                "url": "https://t.co/MVCsywa4YV"
              }
            ]
          }
        },
        "id": "1565981667746914304",
        "location": "People's Republic of China",
        "name": "雪風ちゃん",
        "pinned_tweet_id": "2062168480670240906",
        "profile_image_url": "https://pbs.twimg.com/profile_images/2018975614791999488/Qvf9Q07i_normal.jpg",
        "protected": false,
        "public_metrics": {
          "followers_count": 3163,
          "following_count": 3025,
          "like_count": 110530,
          "listed_count": 7,
          "media_count": 800,
          "tweet_count": 13476
        },
        "url": "https://t.co/MVCsywa4YV",
        "username": "Kagura_Yukikaze",
        "verified": false
      },
      {
        "created_at": "2023-06-13T00:58:23.000Z",
        "description": "She/her | Minor | PJSK / Pocket Mirror | 🎀🎨, 🎈🌟, 🎸🎹, 🌸🐧 ♡ | 🎀🎨 🎈🌟 Parallels CEO | PST | RSYBYF DNI in SP | #sheherformizuki",
        "entities": {
          "description": {
            "hashtags": [
              {
                "end": 123,
                "start": 107,
                "tag": "sheherformizuki"
              }
            ]
          },
          "url": {
            "urls": [
              {
                "display_url": "dawncrimson.straw.page",
                "end": 23,
                "expanded_url": "http://dawncrimson.straw.page",
                "start": 0,
                "url": "https://t.co/mmkrukybPx"
              }
            ]
          }
        },
        "id": "1668422443831291905",
        "location": "今、朝が来るわ𓂃₊ ⊹",
        "name": "Dawn Crimson ☔️🎀🩶",
        "pinned_tweet_id": "2021671423027364186",
        "profile_image_url": "https://pbs.twimg.com/profile_images/2061345182491242496/nddLyXX1_normal.jpg",
        "protected": false,
        "public_metrics": {
          "followers_count": 1206,
          "following_count": 1654,
          "like_count": 205579,
          "listed_count": 6,
          "media_count": 3970,
          "tweet_count": 16137
        },
        "url": "https://t.co/mmkrukybPx",
        "username": "Dawns_Gaming",
        "verified": false
      }
    ]
  }
}