{
  "data": {
    "article": {},
    "attachments": {
      "media_keys": [
        "3_2043673313202069504"
      ],
      "media_source_tweet_id": [
        "2043673848365863223"
      ]
    },
    "author_id": "1565981667746914304",
    "conversation_id": "2045067588531822719",
    "created_at": "2026-04-17T09:11:23.000Z",
    "edit_controls": {
      "editable_until": "2026-04-17T10:11:23.000Z",
      "edits_remaining": 5,
      "is_edit_eligible": false
    },
    "edit_history_tweet_ids": [
      "2045067588531822719"
    ],
    "entities": {
      "mentions": [
        {
          "end": 16,
          "id": "1843877766791606273",
          "start": 3,
          "username": "ddd_uuu87577"
        }
      ],
      "urls": [
        {
          "display_url": "pic.x.com/1IYY6LlnmS",
          "end": 89,
          "expanded_url": "https://x.com/ddd_uuu87577/status/2043673848365863223/photo/1",
          "media_key": "3_2043673313202069504",
          "start": 66,
          "url": "https://t.co/1IYY6LlnmS"
        }
      ]
    },
    "geo": {},
    "id": "2045067588531822719",
    "lang": "zh",
    "note_tweet": {
      "entities": {}
    },
    "possibly_sensitive": false,
    "public_metrics": {
      "bookmark_count": 0,
      "impression_count": 0,
      "like_count": 0,
      "quote_count": 0,
      "reply_count": 0,
      "retweet_count": 217
    },
    "referenced_tweets": [
      {
        "id": "2043673848365863223",
        "type": "retweeted"
      }
    ],
    "reply_settings": "everyone",
    "text": "RT @ddd_uuu87577: 一个残酷的事实是：\n去积极采取行动的人，\n永远是少数。\n所以，\n成功，\n真的是和大多数人无关。 https://t.co/1IYY6LlnmS"
  },
  "includes": {
    "media": [
      {
        "height": 1158,
        "media_key": "3_2043673313202069504",
        "public_metrics": {},
        "type": "photo",
        "url": "https://pbs.twimg.com/media/HFyWDO5a4AAOrwW.jpg",
        "width": 916
      }
    ],
    "tweets": [
      {
        "article": {},
        "attachments": {
          "media_keys": [
            "3_2043673313202069504"
          ],
          "media_source_tweet_id": [
            "2043673848365863223"
          ]
        },
        "author_id": "1565981667746914304",
        "conversation_id": "2045067588531822719",
        "created_at": "2026-04-17T09:11:23.000Z",
        "edit_controls": {
          "editable_until": "2026-04-17T10:11:23.000Z",
          "edits_remaining": 5,
          "is_edit_eligible": false
        },
        "edit_history_tweet_ids": [
          "2045067588531822719"
        ],
        "entities": {
          "mentions": [
            {
              "end": 16,
              "id": "1843877766791606273",
              "start": 3,
              "username": "ddd_uuu87577"
            }
          ],
          "urls": [
            {
              "display_url": "pic.x.com/1IYY6LlnmS",
              "end": 89,
              "expanded_url": "https://x.com/ddd_uuu87577/status/2043673848365863223/photo/1",
              "media_key": "3_2043673313202069504",
              "start": 66,
              "url": "https://t.co/1IYY6LlnmS"
            }
          ]
        },
        "geo": {},
        "id": "2045067588531822719",
        "lang": "zh",
        "note_tweet": {
          "entities": {}
        },
        "possibly_sensitive": false,
        "public_metrics": {
          "bookmark_count": 0,
          "impression_count": 0,
          "like_count": 0,
          "quote_count": 0,
          "reply_count": 0,
          "retweet_count": 217
        },
        "referenced_tweets": [
          {
            "id": "2043673848365863223",
            "type": "retweeted"
          }
        ],
        "reply_settings": "everyone",
        "text": "RT @ddd_uuu87577: 一个残酷的事实是：\n去积极采取行动的人，\n永远是少数。\n所以，\n成功，\n真的是和大多数人无关。 https://t.co/1IYY6LlnmS"
      },
      {
        "article": {},
        "attachments": {
          "media_keys": [
            "3_2043673313202069504"
          ]
        },
        "author_id": "1843877766791606273",
        "conversation_id": "2043673848365863223",
        "created_at": "2026-04-13T12:53:09.000Z",
        "edit_controls": {
          "editable_until": "2026-04-13T13:53:09.000Z",
          "edits_remaining": 5,
          "is_edit_eligible": true
        },
        "edit_history_tweet_ids": [
          "2043673848365863223"
        ],
        "entities": {
          "urls": [
            {
              "display_url": "pic.x.com/1IYY6LlnmS",
              "end": 71,
              "expanded_url": "https://x.com/ddd_uuu87577/status/2043673848365863223/photo/1",
              "media_key": "3_2043673313202069504",
              "start": 48,
              "url": "https://t.co/1IYY6LlnmS"
            }
          ]
        },
        "geo": {},
        "id": "2043673848365863223",
        "lang": "zh",
        "note_tweet": {
          "entities": {}
        },
        "possibly_sensitive": false,
        "public_metrics": {
          "bookmark_count": 236,
          "impression_count": 49936,
          "like_count": 1296,
          "quote_count": 5,
          "reply_count": 26,
          "retweet_count": 217
        },
        "reply_settings": "everyone",
        "text": "一个残酷的事实是：\n去积极采取行动的人，\n永远是少数。\n所以，\n成功，\n真的是和大多数人无关。 https://t.co/1IYY6LlnmS"
      }
    ],
    "users": [
      {
        "created_at": "2022-09-03T08:35:06.000Z",
        "derived": {
          "locations": [
            {
              "country_code": "CN",
              "full_name": "China",
              "geo": {
                "coordinates": [
                  105.0,
                  35.0
                ],
                "type": "Point"
              }
            }
          ]
        },
        "description": "总觉得还有时间，总觉得还有明年，工作太忙日子还长连问候都会忘，别等到世事无常，别等到变了模样\n我想像她一样去拥抱死亡——《124米的距离》",
        "entities": {
          "url": {
            "urls": [
              {
                "display_url": "t.me/Kagura_Yukikaze",
                "end": 23,
                "expanded_url": "https://t.me/Kagura_Yukikaze",
                "start": 0,
                "url": "https://t.co/MVCsywa4YV"
              }
            ]
          }
        },
        "id": "1565981667746914304",
        "location": "People's Republic of China",
        "name": "神楽坂　雪風🍥",
        "pinned_tweet_id": "2034646698086322658",
        "profile_image_url": "https://pbs.twimg.com/profile_images/2018975614791999488/Qvf9Q07i_normal.jpg",
        "protected": false,
        "public_metrics": {
          "followers_count": 2915,
          "following_count": 2815,
          "like_count": 101644,
          "listed_count": 5,
          "media_count": 758,
          "tweet_count": 12330
        },
        "url": "https://t.co/MVCsywa4YV",
        "username": "Kagura_Yukikaze",
        "verified": false
      },
      {
        "created_at": "2024-10-09T04:58:22.000Z",
        "description": "FO 100% (部分图片源自网络，侵删，谢谢)",
        "entities": {
          "url": {
            "urls": [
              {
                "display_url": "youtube.com/@winedance-1a",
                "end": 23,
                "expanded_url": "http://www.youtube.com/@winedance-1a",
                "start": 0,
                "url": "https://t.co/nRsp01HUdV"
              }
            ]
          }
        },
        "id": "1843877766791606273",
        "name": "Wine Dance (fo back 100%)",
        "profile_image_url": "https://pbs.twimg.com/profile_images/1854719337237823491/y126xuRh_normal.jpg",
        "protected": false,
        "public_metrics": {
          "followers_count": 8152,
          "following_count": 5543,
          "like_count": 18065,
          "listed_count": 16,
          "media_count": 2255,
          "tweet_count": 3379
        },
        "url": "https://t.co/nRsp01HUdV",
        "username": "ddd_uuu87577",
        "verified": false
      }
    ]
  }
}